setup.py
nocolon/__init__.py
nocolon.egg-info/PKG-INFO
nocolon.egg-info/SOURCES.txt
nocolon.egg-info/dependency_links.txt
nocolon.egg-info/top_level.txt