Metadata-Version: 1.1
Name: nocolon
Version: 0.0.2
Summary: nocolon is an utf-8 compatible encoding that removes the need of colons in python files.
Home-page: UNKNOWN
Author: Florian Mounier
Author-email: paradoxxx.zero@gmail.com
License: UNKNOWN
Platform: UNKNOWN
Classifier: Development Status :: 3 - Alpha
Classifier: Intended Audience :: Developers
Classifier: Programming Language :: Python :: 3
Provides: nocolon
